<?xml version="1.0" encoding="UTF-8" standalone="no" ?>
<SimscapeMultibodyImportXML version="2.0" xmlns="urn:mathworks:SimscapeMultibody:import" xmlns:xsi="http://www.w3.org/2001/XMLSchema-instance">
<Created by="" on="01/30/25||01:13:19" using="Simscape Multibody Link Version 7.4" from="SolidWorks 33.0.0"/>
<ModelUnits mass="kilogram" length="millimeter"/>
<DataUnits mass="kilogram" length="meter"/>
<RootAssembly name="ball_&amp;_beam" uid="ball_&amp;_beam" version="718">
<AssemblyFile name="ball_&amp;_beam.SLDASM" type="SolidWorks Assembly"/>
<InstanceTree>
<Instance name="Varilla L.step-1" uid="Varilla L.step-1" grounded="true" entityUid="Varilla L.step*:*Predeterminado">
<Transform>
<Rotation>1 0 0 0 1 0 0 0 1</Rotation>
<Translation>0 0 0</Translation>
</Transform>
</Instance>
<Instance name="MG996R.step-1" uid="MG996R.step-1" grounded="true" entityUid="MG996R.step*:*Predeterminado">
<Transform>
<Rotation>1 0 0 0 1 0 0 0 1</Rotation>
<Translation>0 0 0</Translation>
</Transform>
</Instance>
<Instance name="Forquilla G.step-1" uid="Forquilla G.step-1" entityUid="Forquilla G.step*:*Predeterminado">
<Transform>
<Rotation>1 0 0 0 1 0 0 0 1</Rotation>
<Translation>-7.0000000000014495e-05 -0.00010000000000000286 0</Translation>
</Transform>
</Instance>
<Instance name="arm_4pad.step-2" uid="arm_4pad.step-2" entityUid="arm_4pad.step*:*Predeterminado">
<Transform>
<Rotation>0.20187547610131468 0 -0.97941119666300924 0 1 0 0.97941119666300924 0 0.20187547610131468</Rotation>
<Translation>0.39411103288241395 0.00071999999999999441 -0.39415909938134219</Translation>
</Transform>
</Instance>
<Instance name="X 4.step-1" uid="X 4.step-1" grounded="true" entityUid="X 4.step*:*Predeterminado">
<Transform>
<Rotation>1 0 0 0 1 0 0 0 1</Rotation>
<Translation>0 0 0</Translation>
</Transform>
</Instance>
<Instance name="X 3.step-1" uid="X 3.step-1" grounded="true" entityUid="X 3.step*:*Predeterminado">
<Transform>
<Rotation>1 0 0 0 1 0 0 0 1</Rotation>
<Translation>0 0 0</Translation>
</Transform>
</Instance>
<Instance name="Soport servo.step-1" uid="Soport servo.step-1" grounded="true" entityUid="Soport servo.step*:*Predeterminado">
<Transform>
<Rotation>1 0 0 0 1 0 0 0 1</Rotation>
<Translation>0 0 0</Translation>
</Transform>
</Instance>
<Instance name="Base Central.step-1" uid="Base Central.step-1" grounded="true" entityUid="Base Central.step*:*Predeterminado">
<Transform>
<Rotation>1 0 0 0 1 0 0 0 1</Rotation>
<Translation>0 0 0</Translation>
</Transform>
</Instance>
<Instance name="Terra 2.step-1" uid="Terra 2.step-1" grounded="true" entityUid="Terra 2.step*:*Predeterminado">
<Transform>
<Rotation>1 0 0 0 1 0 0 0 1</Rotation>
<Translation>0 0 0</Translation>
</Transform>
</Instance>
<Instance name="X 1.step-1" uid="X 1.step-1" grounded="true" entityUid="X 1.step*:*Predeterminado">
<Transform>
<Rotation>1 0 0 0 1 0 0 0 1</Rotation>
<Translation>0 0 0</Translation>
</Transform>
</Instance>
<Instance name="Terra 1.step-1" uid="Terra 1.step-1" grounded="true" entityUid="Terra 1.step*:*Predeterminado">
<Transform>
<Rotation>1 0 0 0 1 0 0 0 1</Rotation>
<Translation>0 0 0</Translation>
</Transform>
</Instance>
<Instance name="X 2.step-1" uid="X 2.step-1" grounded="true" entityUid="X 2.step*:*Predeterminado">
<Transform>
<Rotation>1 0 0 0 1 0 0 0 1</Rotation>
<Translation>0 0 0</Translation>
</Transform>
</Instance>
<Instance name="Terra 3.step-1" uid="Terra 3.step-1" grounded="true" entityUid="Terra 3.step*:*Predeterminado">
<Transform>
<Rotation>1 0 0 0 1 0 0 0 1</Rotation>
<Translation>0 0 0</Translation>
</Transform>
</Instance>
<Instance name="Base P.step-1" uid="Base P.step-1" entityUid="Base P.step*:*Predeterminado">
<Transform>
<Rotation>0.9969984377369101 3.1811616824451877e-16 0.07742167106282774 -3.1263003425457669e-16 1 0 -0.07742167106282774 0 0.9969984377369101</Rotation>
<Translation>-0.0055859859954775024 -2.999999999986519e-05 0.034423995217874037</Translation>
</Transform>
</Instance>
<Instance name="Roda.step-1" uid="Roda.step-1" entityUid="Roda.step*:*Predeterminado">
<Transform>
<Rotation>0.97941119666405219 -1.8012241248025744e-16 0.20187547609625406 1.8406619217830402e-16 1 0 -0.20187547609625406 0 0.97941119666405219</Rotation>
<Translation>5.45893162079634e-06 -8.0000000000091771e-05 0.089524168991869907</Translation>
</Transform>
</Instance>
<Instance name="Varilla C.step-1" uid="Varilla C.step-1" entityUid="Varilla C.step*:*Predeterminado">
<Transform>
<Rotation>0.9969984377369101 3.178327135827915e-16 0.07742167106282774 -3.1249849398510266e-16 1 0 -0.07742167106282774 0 0.9969984377369101</Rotation>
<Translation>-0.0055859859954772891 -2.9999999999856635e-05 0.0344239952178741</Translation>
</Transform>
</Instance>
<Instance name="Forquilla P.step-1" uid="Forquilla P.step-1" entityUid="Forquilla P.step*:*Predeterminado">
<Transform>
<Rotation>0.9969984377369101 3.1784632127024646e-16 0.07742167106282774 -3.1251705933825987e-16 1 0 -0.07742167106282774 0 0.9969984377369101</Rotation>
<Translation>-0.0055859859951107897 -2.9999999999782683e-05 0.034423995276798992</Translation>
</Transform>
</Instance>
<Instance name="BALANCE.step-1" uid="BALANCE.step-1" entityUid="BALANCE.step*:*Predeterminado">
<Transform>
<Rotation>0.99999891713160094 -6.9489298658252656e-16 -0.0014716438516061488 6.9554329094262001e-16 1 4.413779716704816e-16 0.0014716438516061488 -4.4240108572386562e-16 0.99999891713160094</Rotation>
<Translation>8.6978712636924562e-05 -0.00017000000000022352 -0.00036779565366050628</Translation>
</Transform>
</Instance>
<Instance name="ball-1" uid="ball-1" entityUid="ball*:*Predeterminado">
<Transform>
<Rotation>0.36353626519497861 0.68002366246485113 0.63671752164988882 0.67534458374310702 -0.66316493252829778 0.32267935396239367 0.64167832836783256 0.31269808242556968 -0.70033480004240523</Rotation>
<Translation>0.4040524797500506 0.060326412920756856 0.14275621584808007</Translation>
</Transform>
</Instance>
</InstanceTree>
<Constraints>
<Coincident name="Coincidente7">
<ConstraintGeometry geomType="plane">
<InstancePath>
<Uid>Varilla L.step-1</Uid>
</InstancePath>
<Position>0 -0.074999999999999997 0.092785000000000006</Position>
<Axis>0 0 1</Axis>
</ConstraintGeometry>
<ConstraintGeometry geomType="plane">
<InstancePath>
<Uid>Forquilla G.step-1</Uid>
</InstancePath>
<Position>-0.01 -0.092999999999999999 0.092785000000000006</Position>
<Axis>0 0 -1</Axis>
</ConstraintGeometry>
</Coincident>
<Distance name="Distancia3">
<ConstraintGeometry geomType="plane">
<InstancePath>
<Uid>MG996R.step-1</Uid>
</InstancePath>
<Position>0.43889988009500003 0.045999999999999999 0.044735321784999997</Position>
<Axis>0 1 0</Axis>
</ConstraintGeometry>
<ConstraintGeometry geomType="plane">
<InstancePath>
<Uid>arm_4pad.step-2</Uid>
</InstancePath>
<Position>0.43889988009500014 0.045999999999999999 0.04473532178500006</Position>
<Axis>0 -1 0</Axis>
</ConstraintGeometry>
</Distance>
<Concentric name="Concéntrica2">
<ConstraintGeometry geomType="cylinder">
<InstancePath>
<Uid>MG996R.step-1</Uid>
</InstancePath>
<Position>0.43889988009500003 0.034000000000000002 0.044735321784999997</Position>
<Axis>0 -1 0</Axis>
</ConstraintGeometry>
<ConstraintGeometry geomType="cylinder">
<InstancePath>
<Uid>arm_4pad.step-2</Uid>
</InstancePath>
<Position>0.43889988009500014 0.049000000000000002 0.04473532178500006</Position>
<Axis>0 -1 0</Axis>
</ConstraintGeometry>
</Concentric>
<Coincident name="Coincidente13">
<ConstraintGeometry geomType="plane">
<InstancePath>
<Uid>arm_4pad.step-2</Uid>
</InstancePath>
<Position>0.43889988009500014 0.051499999999999997 0.04473532178500006</Position>
<Axis>0 1 0</Axis>
</ConstraintGeometry>
<ConstraintGeometry geomType="plane">
<InstancePath>
<Uid>Roda.step-1</Uid>
</InstancePath>
<Position>0.41797930898399993 0.052299999999999999 -0.032953880840000005</Position>
<Axis>0 -1 0</Axis>
</ConstraintGeometry>
</Coincident>
<Concentric name="Concéntrica5">
<ConstraintGeometry geomType="cylinder">
<InstancePath>
<Uid>Roda.step-1</Uid>
</InstancePath>
<Position>0.44081288919700001 0.050000000000000003 0.017378017063000004</Position>
<Axis>0 1 0</Axis>
</ConstraintGeometry>
<ConstraintGeometry geomType="cylinder">
<InstancePath>
<Uid>Base P.step-1</Uid>
</InstancePath>
<Position>0.44081954032800008 0.081449999999999995 0.017312034987</Position>
<Axis>0 -1 0</Axis>
</ConstraintGeometry>
</Concentric>
<Coincident name="Coincidente15">
<ConstraintGeometry geomType="plane">
<InstancePath>
<Uid>Roda.step-1</Uid>
</InstancePath>
<Position>0.41797930898399993 0.057299999999999997 -0.032953880840000005</Position>
<Axis>0 1 0</Axis>
</ConstraintGeometry>
<ConstraintGeometry geomType="plane">
<InstancePath>
<Uid>Base P.step-1</Uid>
</InstancePath>
<Position>0.44048042912099999 0.057250000000000002 0.023302444286999999</Position>
<Axis>0 -1 0</Axis>
</ConstraintGeometry>
</Coincident>
<Coincident name="Coincidente16">
<ConstraintGeometry geomType="plane">
<InstancePath>
<Uid>Base P.step-1</Uid>
</InstancePath>
<Position>0.0038284792999999998 -0.04913 0.0018057151859999995</Position>
<Axis>-0.047803796001338383 0 0.99885674502796573</Axis>
</ConstraintGeometry>
<ConstraintGeometry geomType="plane">
<InstancePath>
<Uid>Varilla C.step-1</Uid>
</InstancePath>
<Position>0.0038284793000000015 -0.04913 0.0018057151859999995</Position>
<Axis>0.047803796001338383 0 -0.99885674502796573</Axis>
</ConstraintGeometry>
</Coincident>
<Coincident name="Coincidente21">
<ConstraintGeometry geomType="line">
<InstancePath>
<Uid>Base P.step-1</Uid>
</InstancePath>
<Position>0.44170847135300001 0.068349999999999994 0.029782209014</Position>
<Axis>-0.99840155011261522 0 -0.056518534417725322</Axis>
</ConstraintGeometry>
<ConstraintGeometry geomType="plane">
<InstancePath>
<Uid>Varilla C.step-1</Uid>
</InstancePath>
<Position>0.44044550956400008 0.06834999999999998 0.022701555843000008</Position>
<Axis>0 1 0</Axis>
</ConstraintGeometry>
</Coincident>
<Coincident name="Coincidente22">
<ConstraintGeometry geomType="plane">
<InstancePath>
<Uid>Base P.step-1</Uid>
</InstancePath>
<Position>0.44204368035600006 0.066750000000000004 0.022778041917000003</Position>
<Axis>-0.99885674502796573 0 -0.047803796001338383</Axis>
</ConstraintGeometry>
<ConstraintGeometry geomType="plane">
<InstancePath>
<Uid>Varilla C.step-1</Uid>
</InstancePath>
<Position>0.44204368035600006 0.06674999999999999 0.022778041917000003</Position>
<Axis>0.99885674502796573 0 0.047803796001338383</Axis>
</ConstraintGeometry>
</Coincident>
<Coincident name="Coincidente25">
<ConstraintGeometry geomType="plane">
<InstancePath>
<Uid>Varilla C.step-1</Uid>
</InstancePath>
<Position>0.00098214747900000118 -0.04913 0.061279606042000022</Position>
<Axis>-0.047803796001338383 0 0.99885674502796573</Axis>
</ConstraintGeometry>
<ConstraintGeometry geomType="plane">
<InstancePath>
<Uid>Forquilla P.step-1</Uid>
</InstancePath>
<Position>0.43050729485400002 0.066750000000000004 0.081836039749000014</Position>
<Axis>0.047803796001338383 0 -0.99885674502796573</Axis>
</ConstraintGeometry>
</Coincident>
<Coincident name="Coincidente26">
<ConstraintGeometry geomType="plane">
<InstancePath>
<Uid>Varilla C.step-1</Uid>
</InstancePath>
<Position>0.44204368035600006 0.06674999999999999 0.022778041917000003</Position>
<Axis>0.99885674502796573 0 0.047803796001338383</Axis>
</ConstraintGeometry>
<ConstraintGeometry geomType="plane">
<InstancePath>
<Uid>Forquilla P.step-1</Uid>
</InstancePath>
<Position>0.44148715035700004 0.066750000000000004 0.034406694686000008</Position>
<Axis>-0.99885674502796573 0 -0.047803796001338383</Axis>
</ConstraintGeometry>
</Coincident>
<Coincident name="Coincidente27">
<ConstraintGeometry geomType="plane">
<InstancePath>
<Uid>Varilla C.step-1</Uid>
</InstancePath>
<Position>0.44044550956400008 0.065149999999999986 0.022701555843000008</Position>
<Axis>0 -1 0</Axis>
</ConstraintGeometry>
<ConstraintGeometry geomType="plane">
<InstancePath>
<Uid>Forquilla P.step-1</Uid>
</InstancePath>
<Position>0.43988897956500006 0.06515 0.034330208612999999</Position>
<Axis>0 1 0</Axis>
</ConstraintGeometry>
</Coincident>
<Coincident name="Coincidente31">
<ConstraintGeometry geomType="plane">
<InstancePath>
<Uid>Varilla L.step-1</Uid>
</InstancePath>
<Position>0.25 0.068599999999999994 0.022785</Position>
<Axis>0 1 0</Axis>
</ConstraintGeometry>
<ConstraintGeometry geomType="plane">
<InstancePath>
<Uid>Forquilla G.step-1</Uid>
</InstancePath>
<Position>0.25 0.068699999999999997 0.022785</Position>
<Axis>0 -1 0</Axis>
</ConstraintGeometry>
</Coincident>
<Distance name="Distancia5">
<ConstraintGeometry geomType="plane">
<InstancePath>
<Uid>Forquilla G.step-1</Uid>
</InstancePath>
<Position>0.25169999999999998 0.067000000000000004 0.022785</Position>
<Axis>-1 0 0</Axis>
</ConstraintGeometry>
<ConstraintGeometry geomType="plane">
<InstancePath>
<Uid>Varilla L.step-1</Uid>
</InstancePath>
<Position>0.25159999999999999 0.067000000000000004 0.022785</Position>
<Axis>1 0 0</Axis>
</ConstraintGeometry>
</Distance>
<Distance name="Distancia7">
<ConstraintGeometry geomType="plane">
<InstancePath>
<Uid>BALANCE.step-1</Uid>
</InstancePath>
<Position>0.24934654289400016 0.062 0.10031953215000004</Position>
<Axis>0 -1 0</Axis>
</ConstraintGeometry>
<ConstraintGeometry geomType="plane">
<InstancePath>
<Uid>Forquilla G.step-1</Uid>
</InstancePath>
<Position>0.20599999999999999 0.061899999999999997 0.106485</Position>
<Axis>0 1 0</Axis>
</ConstraintGeometry>
</Distance>
<Concentric name="Concéntrica10">
<ConstraintGeometry geomType="cylinder">
<InstancePath>
<Uid>Forquilla G.step-1</Uid>
</InstancePath>
<Position>0.25 0.055 0.106485</Position>
<Axis>0 1 0</Axis>
</ConstraintGeometry>
<ConstraintGeometry geomType="cylinder">
<InstancePath>
<Uid>BALANCE.step-1</Uid>
</InstancePath>
<Position>0.25000000000000011 0.059999999999999998 0.10648500000000004</Position>
<Axis>0 1 0</Axis>
</ConstraintGeometry>
</Concentric>
<Parallel name="Paralelo30">
<ConstraintGeometry geomType="plane">
<InstancePath>
<Uid>Forquilla P.step-1</Uid>
</InstancePath>
<Position>0.42817908644900005 0.064999999999999988 0.086554214638999996</Position>
<Axis>0 1 0</Axis>
</ConstraintGeometry>
<ConstraintGeometry geomType="plane">
<InstancePath>
<Uid>BALANCE.step-1</Uid>
</InstancePath>
<Position>-0.016599223870000006 0.065250000000000002 0.084033161390000041</Position>
<Axis>0 -1 0</Axis>
</ConstraintGeometry>
</Parallel>
<Concentric name="Concéntrica11">
<ConstraintGeometry geomType="cylinder">
<InstancePath>
<Uid>Forquilla P.step-1</Uid>
</InstancePath>
<Position>0.4373207647070001 0.055199999999999999 0.087992866305000014</Position>
<Axis>0 1 0</Axis>
</ConstraintGeometry>
<ConstraintGeometry geomType="cylinder">
<InstancePath>
<Uid>BALANCE.step-1</Uid>
</InstancePath>
<Position>0.43727771540200022 0.055 0.088019015028000053</Position>
<Axis>0 1 0</Axis>
</ConstraintGeometry>
</Concentric>
<Concentric name="Concéntrica12">
<ConstraintGeometry geomType="cylinder">
<InstancePath>
<Uid>arm_4pad.step-2</Uid>
</InstancePath>
<Position>0.43889988009500014 0.049599999999999998 0.04473532178500006</Position>
<Axis>0 1 0</Axis>
</ConstraintGeometry>
<ConstraintGeometry geomType="cylinder">
<InstancePath>
<Uid>Roda.step-1</Uid>
</InstancePath>
<Position>0.43889988009500003 0.057299999999999997 0.04473532178499999</Position>
<Axis>0 -1 0</Axis>
</ConstraintGeometry>
</Concentric>
<Concentric name="Concéntrica13">
<ConstraintGeometry geomType="cylinder">
<InstancePath>
<Uid>arm_4pad.step-2</Uid>
</InstancePath>
<Position>0.43793026511000011 0.049000000000000002 0.058601462082999989</Position>
<Axis>0 -1 0</Axis>
</ConstraintGeometry>
<ConstraintGeometry geomType="cylinder">
<InstancePath>
<Uid>Roda.step-1</Uid>
</InstancePath>
<Position>0.42503373979599995 0.052099999999999994 0.043765706800000012</Position>
<Axis>0 1 0</Axis>
</ConstraintGeometry>
</Concentric>
<Concentric name="Concéntrica14">
<ConstraintGeometry geomType="cylinder">
<InstancePath>
<Uid>arm_4pad.step-2</Uid>
</InstancePath>
<Position>0.43986949508000012 0.049000000000000002 0.030869181485999986</Position>
<Axis>0 -1 0</Axis>
</ConstraintGeometry>
<ConstraintGeometry geomType="cylinder">
<InstancePath>
<Uid>Roda.step-1</Uid>
</InstancePath>
<Position>0.45276602039299996 0.052099999999999994 0.045704936769999968</Position>
<Axis>0 1 0</Axis>
</ConstraintGeometry>
</Concentric>
<Tangent name="Tangente13">
<ConstraintGeometry geomType="plane">
<InstancePath>
<Uid>BALANCE.step-1</Uid>
</InstancePath>
<Position>0.18798239581300008 0.057450000000000001 0.13331530773000003</Position>
<Axis>0.070506412995893733 0.74329414595671028 0.66523879796125651</Axis>
</ConstraintGeometry>
<ConstraintGeometry geomType="sphere">
<InstancePath>
<Uid>ball-1</Uid>
</InstancePath>
<Position>0 0 0.020000000000000073</Position>
</ConstraintGeometry>
</Tangent>
<Tangent name="Tangente14">
<ConstraintGeometry geomType="plane">
<InstancePath>
<Uid>BALANCE.step-1</Uid>
</InstancePath>
<Position>0.18798239581300008 0.076450000000000004 0.13331530773000003</Position>
<Axis>0.070506412995893733 -0.74329414595671028 0.66523879796125651</Axis>
</ConstraintGeometry>
<ConstraintGeometry geomType="sphere">
<InstancePath>
<Uid>ball-1</Uid>
</InstancePath>
<Position>0 0 0.020000000000000073</Position>
</ConstraintGeometry>
</Tangent>
<Tangent name="Tangente15">
<ConstraintGeometry geomType="plane">
<InstancePath>
<Uid>BALANCE.step-1</Uid>
</InstancePath>
<Position>0.18798239581300008 0.076450000000000004 0.13331530773000003</Position>
<Axis>0.070506412995893733 -0.74329414595671028 0.66523879796125651</Axis>
</ConstraintGeometry>
<ConstraintGeometry geomType="sphere">
<InstancePath>
<Uid>ball-1</Uid>
</InstancePath>
<Position>0 0 0.020000000000000073</Position>
</ConstraintGeometry>
</Tangent>
<Tangent name="Tangente16">
<ConstraintGeometry geomType="plane">
<InstancePath>
<Uid>BALANCE.step-1</Uid>
</InstancePath>
<Position>0.18798239581300008 0.057450000000000001 0.13331530773000003</Position>
<Axis>0.070506412995893733 0.74329414595671028 0.66523879796125651</Axis>
</ConstraintGeometry>
<ConstraintGeometry geomType="sphere">
<InstancePath>
<Uid>ball-1</Uid>
</InstancePath>
<Position>0 0 0.020000000000000073</Position>
</ConstraintGeometry>
</Tangent>
<Tangent name="Tangente17">
<ConstraintGeometry geomType="plane">
<InstancePath>
<Uid>BALANCE.step-1</Uid>
</InstancePath>
<Position>0.18798239581300008 0.076450000000000004 0.13331530773000003</Position>
<Axis>0.070506412995893733 -0.74329414595671028 0.66523879796125651</Axis>
</ConstraintGeometry>
<ConstraintGeometry geomType="sphere">
<InstancePath>
<Uid>ball-1</Uid>
</InstancePath>
<Position>0 0 0.020000000000000073</Position>
</ConstraintGeometry>
</Tangent>
<Tangent name="Tangente18">
<ConstraintGeometry geomType="plane">
<InstancePath>
<Uid>BALANCE.step-1</Uid>
</InstancePath>
<Position>0.18798239581300008 0.057450000000000001 0.13331530773000003</Position>
<Axis>0.070506412995893733 0.74329414595671028 0.66523879796125651</Axis>
</ConstraintGeometry>
<ConstraintGeometry geomType="sphere">
<InstancePath>
<Uid>ball-1</Uid>
</InstancePath>
<Position>0 0 0.020000000000000073</Position>
</ConstraintGeometry>
</Tangent>
</Constraints>
</RootAssembly>
<Assemblies>
</Assemblies>
<Parts>
<Part name="BALANCE.step" uid="BALANCE.step*:*Predeterminado" version="114">
<ModelUnits mass="kilogram" length="millimeter"/>
<PartFile name="BALANCE.step.SLDPRT" type="SolidWorks Part"/>
<MassProperties>
<Mass>0.062175351395951095</Mass>
<CenterOfMass>0.21939788811175828 0.066835680575401971 0.13096677629526471</CenterOfMass>
<Inertia>3.2439410654511032e-05 0.0010925407300132358 0.0010746456804633536 6.138669047730268e-07 0.00014369926595303095 -2.2944034275997585e-06</Inertia>
</MassProperties>
<GeometryFile name="BALANCE.step_Predeterminado_sldprt.STEP" type="STEP"/>
<VisualProperties>
<Ambient r="0" g="0" b="1" a="1"/>
<Diffuse r="0" g="0" b="1" a="1"/>
<Specular r="0" g="0" b="0.5" a="1"/>
<Emissive r="0" g="0" b="0" a="1"/>
<Shininess>0.3125</Shininess>
</VisualProperties>
</Part>
<Part name="Base Central.step" uid="Base Central.step*:*Predeterminado" version="114">
<ModelUnits mass="kilogram" length="millimeter"/>
<PartFile name="Base Central.step.SLDPRT" type="SolidWorks Part"/>
<MassProperties>
<Mass>0.14187932669232528</Mass>
<CenterOfMass>0.24999999689920141 0.066999994556405096 0.017357690622019983</CenterOfMass>
<Inertia>7.0663561595731139e-05 7.066333788282839e-05 0.00011889850987469916 -4.9039569458930029e-13 2.3554987850314777e-12 6.2954270665186493e-12</Inertia>
</MassProperties>
<GeometryFile name="Base Central.step_Predeterminado_sldprt.STEP" type="STEP"/>
<VisualProperties>
<Ambient r="0.792156862745098" g="0.81960784313725488" b="0.93333333333333335" a="1"/>
<Diffuse r="0.792156862745098" g="0.81960784313725488" b="0.93333333333333335" a="1"/>
<Specular r="0.396078431372549" g="0.40980392156862744" b="0.46666666666666667" a="1"/>
<Emissive r="0" g="0" b="0" a="1"/>
<Shininess>0.3125</Shininess>
</VisualProperties>
</Part>
<Part name="Base P.step" uid="Base P.step*:*Predeterminado" version="114">
<ModelUnits mass="kilogram" length="millimeter"/>
<PartFile name="Base P.step.SLDPRT" type="SolidWorks Part"/>
<MassProperties>
<Mass>0.0026098348473334743</Mass>
<CenterOfMass>0.4405916319876817 0.064519773629359733 0.021355455696898108</CenterOfMass>
<Inertia>1.0504526098736345e-07 9.2580544140799071e-08 7.1520061924443676e-08 1.4065439984161535e-09 1.8925033924903015e-09 -8.5394634189229057e-11</Inertia>
</MassProperties>
<GeometryFile name="Base P.step_Predeterminado_sldprt.STEP" type="STEP"/>
<VisualProperties>
<Ambient r="0.792156862745098" g="0.81960784313725488" b="0.93333333333333335" a="1"/>
<Diffuse r="0.792156862745098" g="0.81960784313725488" b="0.93333333333333335" a="1"/>
<Specular r="0.396078431372549" g="0.40980392156862744" b="0.46666666666666667" a="1"/>
<Emissive r="0" g="0" b="0" a="1"/>
<Shininess>0.3125</Shininess>
</VisualProperties>
</Part>
<Part name="Forquilla G.step" uid="Forquilla G.step*:*Predeterminado" version="114">
<ModelUnits mass="kilogram" length="millimeter"/>
<PartFile name="Forquilla G.step.SLDPRT" type="SolidWorks Part"/>
<MassProperties>
<Mass>0.0048302084827955838</Mass>
<CenterOfMass>0.24999466699622289 0.065908304164742512 0.097492418421970123</CenterOfMass>
<Inertia>3.9584109207033679e-07 3.928049277984221e-07 2.1836974328394216e-07 3.8499599493405826e-08 3.8748711260857527e-11 9.2885026694229074e-11</Inertia>
</MassProperties>
<GeometryFile name="Forquilla G.step_Predeterminado_sldprt.STEP" type="STEP"/>
<VisualProperties>
<Ambient r="0" g="0" b="0" a="1"/>
<Diffuse r="0" g="0" b="0" a="1"/>
<Specular r="0" g="0" b="0" a="1"/>
<Emissive r="0" g="0" b="0" a="1"/>
<Shininess>0.3125</Shininess>
</VisualProperties>
</Part>
<Part name="Forquilla P.step" uid="Forquilla P.step*:*Predeterminado" version="114">
<ModelUnits mass="kilogram" length="millimeter"/>
<PartFile name="Forquilla P.step.SLDPRT" type="SolidWorks Part"/>
<MassProperties>
<Mass>0.00079683796358188139</Mass>
<CenterOfMass>0.4375891618846483 0.066750000011432054 0.082384724985906585</CenterOfMass>
<Inertia>2.0559609569024344e-08 1.9222352927175408e-08 1.2005513391330814e-08 0 4.1032636129906522e-10 3.0479147132129139e-15</Inertia>
</MassProperties>
<GeometryFile name="Forquilla P.step_Predeterminado_sldprt.STEP" type="STEP"/>
<VisualProperties>
<Ambient r="0.792156862745098" g="0.81960784313725488" b="0.93333333333333335" a="1"/>
<Diffuse r="0.792156862745098" g="0.81960784313725488" b="0.93333333333333335" a="1"/>
<Specular r="0.396078431372549" g="0.40980392156862744" b="0.46666666666666667" a="1"/>
<Emissive r="0" g="0" b="0" a="1"/>
<Shininess>0.3125</Shininess>
</VisualProperties>
</Part>
<Part name="MG996R.step" uid="MG996R.step*:*Predeterminado" version="114">
<ModelUnits mass="kilogram" length="millimeter"/>
<PartFile name="MG996R.step.SLDPRT" type="SolidWorks Part"/>
<MassProperties>
<Mass>0.030831672519766543</Mass>
<CenterOfMass>0.44890358327549201 0.025068600363654173 0.044735327129921093</CenterOfMass>
<Inertia>4.688202875924986e-06 5.3225446537577823e-06 7.9574520560236926e-06 -3.2763115974823e-12 -1.5633604476206363e-12 1.0563311789815483e-08</Inertia>
</MassProperties>
<GeometryFile name="MG996R.step_Predeterminado_sldprt.STEP" type="STEP"/>
<VisualProperties>
<Ambient r="0.792156862745098" g="0.81960784313725488" b="0.93333333333333335" a="1"/>
<Diffuse r="0.792156862745098" g="0.81960784313725488" b="0.93333333333333335" a="1"/>
<Specular r="0.396078431372549" g="0.40980392156862744" b="0.46666666666666667" a="1"/>
<Emissive r="0" g="0" b="0" a="1"/>
<Shininess>0.3125</Shininess>
</VisualProperties>
</Part>
<Part name="Roda.step" uid="Roda.step*:*Predeterminado" version="114">
<ModelUnits mass="kilogram" length="millimeter"/>
<PartFile name="Roda.step.SLDPRT" type="SolidWorks Part"/>
<MassProperties>
<Mass>0.013871669438937731</Mass>
<CenterOfMass>0.43889500603691523 0.054800000000000001 0.044805024063017243</CenterOfMass>
<Inertia>3.1437403146706227e-06 6.2565741217160291e-06 3.1701294594679219e-06 0 -1.8543762178806693e-09 0</Inertia>
</MassProperties>
<GeometryFile name="Roda.step_Predeterminado_sldprt.STEP" type="STEP"/>
<VisualProperties>
<Ambient r="0.11372549019607843" g="0.25098039215686274" b="0.85098039215686272" a="1"/>
<Diffuse r="0.11372549019607843" g="0.25098039215686274" b="0.85098039215686272" a="1"/>
<Specular r="0.056862745098039215" g="0.12549019607843137" b="0.42549019607843136" a="1"/>
<Emissive r="0" g="0" b="0" a="1"/>
<Shininess>0.3125</Shininess>
</VisualProperties>
</Part>
<Part name="Soport servo.step" uid="Soport servo.step*:*Predeterminado" version="114">
<ModelUnits mass="kilogram" length="millimeter"/>
<PartFile name="Soport servo.step.SLDPRT" type="SolidWorks Part"/>
<MassProperties>
<Mass>0.080525048633781154</Mass>
<CenterOfMass>0.4491370112890341 0.016342092473958042 0.022143933053425522</CenterOfMass>
<Inertia>2.1935021363464206e-05 4.9654934011813132e-05 4.4379121376900619e-05 1.1944935284629632e-06 -4.3831941314350312e-07 -1.5476376471261881e-08</Inertia>
</MassProperties>
<GeometryFile name="Soport servo.step_Predeterminado_sldprt.STEP" type="STEP"/>
<VisualProperties>
<Ambient r="0.90196078431372551" g="0.53725490196078429" b="0.1803921568627451" a="1"/>
<Diffuse r="0.90196078431372551" g="0.53725490196078429" b="0.1803921568627451" a="1"/>
<Specular r="0.45098039215686275" g="0.26862745098039215" b="0.090196078431372548" a="1"/>
<Emissive r="0" g="0" b="0" a="1"/>
<Shininess>0.3125</Shininess>
</VisualProperties>
</Part>
<Part name="Terra 1.step" uid="Terra 1.step*:*Predeterminado" version="114">
<ModelUnits mass="kilogram" length="millimeter"/>
<PartFile name="Terra 1.step.SLDPRT" type="SolidWorks Part"/>
<MassProperties>
<Mass>0.1101593906381927</Mass>
<CenterOfMass>0.082405524569307984 0.067003005054974765 0.0025000000000000001</CenterOfMass>
<Inertia>0.00016520465441459807 0.00024853589923674678 0.00041328155619035293 0 0 -2.638294500722643e-08</Inertia>
</MassProperties>
<GeometryFile name="Terra 1.step_Predeterminado_sldprt.STEP" type="STEP"/>
<VisualProperties>
<Ambient r="0.80000000000000004" g="0.80000000000000004" b="0.80000000000000004" a="1"/>
<Diffuse r="0.80000000000000004" g="0.80000000000000004" b="0.80000000000000004" a="1"/>
<Specular r="0.40000000000000002" g="0.40000000000000002" b="0.40000000000000002" a="1"/>
<Emissive r="0" g="0" b="0" a="1"/>
<Shininess>0.3125</Shininess>
</VisualProperties>
</Part>
<Part name="Terra 2.step" uid="Terra 2.step*:*Predeterminado" version="114">
<ModelUnits mass="kilogram" length="millimeter"/>
<PartFile name="Terra 2.step.SLDPRT" type="SolidWorks Part"/>
<MassProperties>
<Mass>0.10942400313708146</Mass>
<CenterOfMass>0.24747454228034721 0.067005946573730005 0.0025018525931889903</CenterOfMass>
<Inertia>0.00016440891320870644 0.00024557750809910806 0.00040953048871251828 1.2054785020530122e-12 -5.1195614947481886e-10 4.2823802367916581e-10</Inertia>
</MassProperties>
<GeometryFile name="Terra 2.step_Predeterminado_sldprt.STEP" type="STEP"/>
<VisualProperties>
<Ambient r="0.80000000000000004" g="0.80000000000000004" b="0.80000000000000004" a="1"/>
<Diffuse r="0.80000000000000004" g="0.80000000000000004" b="0.80000000000000004" a="1"/>
<Specular r="0.40000000000000002" g="0.40000000000000002" b="0.40000000000000002" a="1"/>
<Emissive r="0" g="0" b="0" a="1"/>
<Shininess>0.3125</Shininess>
</VisualProperties>
</Part>
<Part name="Terra 3.step" uid="Terra 3.step*:*Predeterminado" version="114">
<ModelUnits mass="kilogram" length="millimeter"/>
<PartFile name="Terra 3.step.SLDPRT" type="SolidWorks Part"/>
<MassProperties>
<Mass>0.11314764891539314</Mass>
<CenterOfMass>0.41493461695109668 0.067145859775869426 0.0025017950342536548</CenterOfMass>
<Inertia>0.00016933479491953847 0.00027068638511317596 0.00043954973222472374 1.0184819966083428e-08 -6.8413756112614011e-09 -5.1694127599364343e-07</Inertia>
</MassProperties>
<GeometryFile name="Terra 3.step_Predeterminado_sldprt.STEP" type="STEP"/>
<VisualProperties>
<Ambient r="0.80000000000000004" g="0.80000000000000004" b="0.80000000000000004" a="1"/>
<Diffuse r="0.80000000000000004" g="0.80000000000000004" b="0.80000000000000004" a="1"/>
<Specular r="0.40000000000000002" g="0.40000000000000002" b="0.40000000000000002" a="1"/>
<Emissive r="0" g="0" b="0" a="1"/>
<Shininess>0.3125</Shininess>
</VisualProperties>
</Part>
<Part name="Varilla C.step" uid="Varilla C.step*:*Predeterminado" version="114">
<ModelUnits mass="kilogram" length="millimeter"/>
<PartFile name="Varilla C.step.SLDPRT" type="SolidWorks Part"/>
<MassProperties>
<Mass>0.00056775677941581335</Mass>
<CenterOfMass>0.4390223276021476 0.06674999683472356 0.052438806482753807</CenterOfMass>
<Inertia>1.5414488942432912e-07 1.5450108899494149e-07 1.367083833348446e-09 -4.5630072819443424e-14 7.3283726079171731e-09 -1.4210704631842916e-15</Inertia>
</MassProperties>
<GeometryFile name="Varilla C.step_Predeterminado_sldprt.STEP" type="STEP"/>
<VisualProperties>
<Ambient r="0" g="0" b="1" a="1"/>
<Diffuse r="0" g="0" b="1" a="1"/>
<Specular r="0" g="0" b="0.5" a="1"/>
<Emissive r="0" g="0" b="0" a="1"/>
<Shininess>0.3125</Shininess>
</VisualProperties>
</Part>
<Part name="Varilla L.step" uid="Varilla L.step*:*Predeterminado" version="114">
<ModelUnits mass="kilogram" length="millimeter"/>
<PartFile name="Varilla L.step.SLDPRT" type="SolidWorks Part"/>
<MassProperties>
<Mass>0.00078747733980583622</Mass>
<CenterOfMass>0.24999999957497457 0.066999995615524013 0.052176336295997459</CenterOfMass>
<Inertia>4.0841322557532441e-07 4.0840781578015419e-07 1.4055909184518164e-09 1.3042452050863346e-13 6.3061868100703487e-14 2.1140085379991597e-15</Inertia>
</MassProperties>
<GeometryFile name="Varilla L.step_Predeterminado_sldprt.STEP" type="STEP"/>
<VisualProperties>
<Ambient r="0" g="0" b="1" a="1"/>
<Diffuse r="0" g="0" b="1" a="1"/>
<Specular r="0" g="0" b="0.5" a="1"/>
<Emissive r="0" g="0" b="0" a="1"/>
<Shininess>0.3125</Shininess>
</VisualProperties>
</Part>
<Part name="X 1.step" uid="X 1.step*:*Predeterminado" version="114">
<ModelUnits mass="kilogram" length="millimeter"/>
<PartFile name="X 1.step.SLDPRT" type="SolidWorks Part"/>
<MassProperties>
<Mass>0.00029670719157114236</Mass>
<CenterOfMass>0.33007862705307961 0.098491116311533636 0.0025999999999999999</CenterOfMass>
<Inertia>3.906534871376614e-09 3.9065835781903859e-09 6.576838484701947e-09 0 0 0</Inertia>
</MassProperties>
<GeometryFile name="X 1.step_Predeterminado_sldprt.STEP" type="STEP"/>
<VisualProperties>
<Ambient r="0" g="0" b="1" a="1"/>
<Diffuse r="0" g="0" b="1" a="1"/>
<Specular r="0" g="0" b="0.5" a="1"/>
<Emissive r="0" g="0" b="0" a="1"/>
<Shininess>0.3125</Shininess>
</VisualProperties>
</Part>
<Part name="X 2.step" uid="X 2.step*:*Predeterminado" version="114">
<ModelUnits mass="kilogram" length="millimeter"/>
<PartFile name="X 2.step.SLDPRT" type="SolidWorks Part"/>
<MassProperties>
<Mass>0.00029670719157114285</Mass>
<CenterOfMass>0.1650786270530796 0.098491116311533636 0.0025000000000000001</CenterOfMass>
<Inertia>3.9065348713766206e-09 3.9065835781903925e-09 6.5768384847019594e-09 0 0 0</Inertia>
</MassProperties>
<GeometryFile name="X 2.step_Predeterminado_sldprt.STEP" type="STEP"/>
<VisualProperties>
<Ambient r="0" g="0" b="1" a="1"/>
<Diffuse r="0" g="0" b="1" a="1"/>
<Specular r="0" g="0" b="0.5" a="1"/>
<Emissive r="0" g="0" b="0" a="1"/>
<Shininess>0.3125</Shininess>
</VisualProperties>
</Part>
<Part name="X 3.step" uid="X 3.step*:*Predeterminado" version="114">
<ModelUnits mass="kilogram" length="millimeter"/>
<PartFile name="X 3.step.SLDPRT" type="SolidWorks Part"/>
<MassProperties>
<Mass>0.00029670719157114236</Mass>
<CenterOfMass>0.33007862705307961 0.03349111631153364 0.0025000000000000001</CenterOfMass>
<Inertia>3.9065348713766032e-09 3.9065835781903867e-09 6.5768384847019379e-09 0 0 0</Inertia>
</MassProperties>
<GeometryFile name="X 3.step_Predeterminado_sldprt.STEP" type="STEP"/>
<VisualProperties>
<Ambient r="0" g="0" b="1" a="1"/>
<Diffuse r="0" g="0" b="1" a="1"/>
<Specular r="0" g="0" b="0.5" a="1"/>
<Emissive r="0" g="0" b="0" a="1"/>
<Shininess>0.3125</Shininess>
</VisualProperties>
</Part>
<Part name="X 4.step" uid="X 4.step*:*Predeterminado" version="114">
<ModelUnits mass="kilogram" length="millimeter"/>
<PartFile name="X 4.step.SLDPRT" type="SolidWorks Part"/>
<MassProperties>
<Mass>0.00029670719157114301</Mass>
<CenterOfMass>0.1650786270530796 0.033491116311533634 0.0025000000000000001</CenterOfMass>
<Inertia>3.9065348713766131e-09 3.9065835781903925e-09 6.5768384847019511e-09 0 0 0</Inertia>
</MassProperties>
<GeometryFile name="X 4.step_Predeterminado_sldprt.STEP" type="STEP"/>
<VisualProperties>
<Ambient r="0" g="0" b="1" a="1"/>
<Diffuse r="0" g="0" b="1" a="1"/>
<Specular r="0" g="0" b="0.5" a="1"/>
<Emissive r="0" g="0" b="0" a="1"/>
<Shininess>0.3125</Shininess>
</VisualProperties>
</Part>
<Part name="arm_4pad.step" uid="arm_4pad.step*:*Predeterminado" version="114">
<ModelUnits mass="kilogram" length="millimeter"/>
<PartFile name="arm_4pad.step.SLDPRT" type="SolidWorks Part"/>
<MassProperties>
<Mass>0.0012138264646507403</Mass>
<CenterOfMass>0.43889988012171433 0.050011698555363762 0.044735321786445695</CenterOfMass>
<Inertia>7.2726247203081186e-08 1.4256125884055654e-07 7.2726247113994483e-08 0 0 0</Inertia>
</MassProperties>
<GeometryFile name="arm_4pad.step_Predeterminado_sldprt.STEP" type="STEP"/>
<VisualProperties>
<Ambient r="0.80000000000000004" g="0.80000000000000004" b="0.80000000000000004" a="1"/>
<Diffuse r="0.80000000000000004" g="0.80000000000000004" b="0.80000000000000004" a="1"/>
<Specular r="0.40000000000000002" g="0.40000000000000002" b="0.40000000000000002" a="1"/>
<Emissive r="0" g="0" b="0" a="1"/>
<Shininess>0.3125</Shininess>
</VisualProperties>
</Part>
<Part name="ball" uid="ball*:*Predeterminado" version="130">
<ModelUnits mass="kilogram" length="millimeter"/>
<PartFile name="ball.SLDPRT" type="SolidWorks Part"/>
<MassProperties>
<Mass>0.047584656726373409</Mass>
<CenterOfMass>0 0 0.019999999999999997</CenterOfMass>
<Inertia>7.6135450762197454e-06 7.6135450762197454e-06 7.6135450762197463e-06 0 0 0</Inertia>
</MassProperties>
<GeometryFile name="ball_Predeterminado_sldprt.STEP" type="STEP"/>
<VisualProperties>
<Ambient r="1" g="1" b="1" a="1"/>
<Diffuse r="1" g="1" b="1" a="1"/>
<Specular r="1" g="1" b="1" a="1"/>
<Emissive r="0" g="0" b="0" a="1"/>
<Shininess>0.3125</Shininess>
</VisualProperties>
</Part>
</Parts>
</SimscapeMultibodyImportXML>
